{
  "project_info": {
    "project_number": "469895547222",
    "project_id": "mobile-application-fc740",
    "storage_bucket": "mobile-application-fc740.firebasestorage.app"
  },
  "client": [
    {
      "client_info": {
        "mobilesdk_app_id": "1:469895547222:android:933621005bb79d54fa6ef7",
        "android_client_info": {
          "package_name": "com.example.worldcashbox"
        }
      },
      "oauth_client": [],
      "api_key": [
        {
          "current_key": "AIzaSyAhdPttwXDpu_M6QM3ihDBqVekXguUqJM8"
        }
      ],
      "services": {
        "appinvite_service": {
          "other_platform_oauth_client": []
        }
      }
    }
  ],
  "configuration_version": "1"
}
